snakemake_executor_plugin_flux/__init__.py
snakemake_executor_plugin_flux/executor.py
snakemake_executor_plugin_flux-0.1.1.dist-info/LICENSE
snakemake_executor_plugin_flux-0.1.1.dist-info/METADATA
snakemake_executor_plugin_flux-0.1.1.dist-info/NOTICE
snakemake_executor_plugin_flux-0.1.1.dist-info/WHEEL
snakemake_executor_plugin_flux-0.1.1.dist-info/RECORD
