Metadata-Version: 2.1
Name: snakemake-executor-plugin-flux
Version: 0.1.1
Summary: A snakemake executor plugin for the Flux scheduler
Home-page: https://github.com/snakemake/snakemake-executor-plugin-flux
License: MIT
Keywords: snakemake,plugin,executor,flux,flux-framework
Author: vsoch
Author-email: vsoch@users.noreply.github.com
Requires-Python: >=3.11,<4.0
Classifier: License :: OSI Approved :: MIT License
Classifier: Programming Language :: Python :: 3
Classifier: Programming Language :: Python :: 3.11
Classifier: Programming Language :: Python :: 3.12
Requires-Dist: snakemake-interface-common (>=1.14.0,<2.0.0)
Requires-Dist: snakemake-interface-executor-plugins (>=9.0.0,<10.0.0)
Project-URL: Documentation, https://snakemake.github.io/snakemake-plugin-catalog/plugins/executor/flux.html
Project-URL: Repository, https://github.com/snakemake/snakemake-executor-plugin-flux
